{
  "title": {
    "zh_cn": "绰巡林风",
    "zh_tw": "綽巡林風",
    "en_us": "Winding Through Avidya",
    "ko_kr": "Winding Through Avidya",
    "ja_jp": "アビディアを巡る風",
    "es_es": "Winding Through Avidya",
    "fr_fr": "Winding Through Avidya",
    "ru_ru": "Winding Through Avidya",
    "th_th": "Winding Through Avidya",
    "vi_vn": "Winding Through Avidya",
    "de_de": "Winding Through Avidya",
    "id_id": "Winding Through Avidya",
    "pt_pt": "Winding Through Avidya"
  },
  "country": {
    "zh_cn": "须弥",
    "zh_tw": "須彌",
    "en_us": "Sumeru",
    "ko_kr": "수메르",
    "ja_jp": "スメール",
    "es_es": "Sumeru",
    "fr_fr": "Sumeru",
    "ru_ru": "Сумеру",
    "th_th": "Sumeru",
    "vi_vn": "Sumeru",
    "de_de": "Sumeru",
    "id_id": "Sumeru",
    "pt_pt": "Sumeru",
    "tr_tr": "Sumeru",
    "it_it": "Sumeru"
  },
  "album": {
    "zh_cn": "闪耀的群星3（提纳里）",
    "zh_tw": "閃耀的群星3（提納里）",
    "en_us": "The Stellar Moments Vol. 3 (Tighnari)",
    "ko_kr": "빛나는 뭇별3（타이나리）",
    "ja_jp": "輝く星々Vol.3（ティナリ）",
    "es_es": "Los momentos estelares 3 (Tignari)",
    "fr_fr": "The Stellar Moments Vol. 3 ( Tighnari )",
    "ru_ru": "The Stellar Moments Vol. 3 (Тигнари)",
    "th_th": "The Stellar Moments Vol. 3 (Tighnari)",
    "vi_vn": "The Stellar Moments Vol. 3 (Tighnari)",
    "de_de": "The Stellar Moments Vol. 3 (Tighnari)",
    "id_id": "The Stellar Moments Vol. 3 (Tighnari)",
    "pt_pt": "The Stellar Moments Vol. 3 (Tighnari)",
    "tr_tr": "The Stellar Moments Vol. 3 (Tighnari)",
    "it_it": "The Stellar Moments Vol. 3 (Tighnari)"
  },
  "link_ytmusic": "",
  "duration": 131,
  "bpm": 103,
  "level": 7,
  "base": 0.02,
  "score": [],
  "measure": {},
  "bpm_act": {
    "0": "静かめになってからBPMが不安定すぎる"
  }
}